<?xml version="1.0" encoding="utf-8"?>
<!--Created with SharpOcarina 1.32-->
<ZScene cloneid="0" xmlns="clr-namespace:SharpOcarina;assembly=SharpOcarina">
  <Name>unnamed</Name>
  <Scale>1</Scale>
  <Music>2</Music>
  <NightSFX>0</NightSFX>
  <Skybox>0</Skybox>
  <Weather>0</Weather>
  <SpecialObject>3</SpecialObject>
  <ElfMessage>0</ElfMessage>
  <InjectOffset>47185920</InjectOffset>
  <SceneNumber>108</SceneNumber>
  <Reverb>0</Reverb>
  <CameraMovement>0</CameraMovement>
  <WorldMap>0</WorldMap>
  <SceneSettings>0</SceneSettings>
  <OutdoorLight>true</OutdoorLight>
  <FixedCameraXPos>0</FixedCameraXPos>
  <FixedCameraYPos>0</FixedCameraYPos>
  <FixedCameraZPos>0</FixedCameraZPos>
  <FixedCameraXRot>0</FixedCameraXRot>
  <FixedCameraYRot>0</FixedCameraYRot>
  <FixedCameraZRot>0</FixedCameraZRot>
  <TimeCtrl>0</TimeCtrl>
  <SkyboxType>0</SkyboxType>
  <Cloudy>false</Cloudy>
  <ContinualInject>true</ContinualInject>
  <NewRoomMode>false</NewRoomMode>
  <Prerendered>false</Prerendered>
  <PregeneratedMesh>false</PregeneratedMesh>
  <JFIFpath></JFIFpath>
  <CutsceneEntrance>0</CutsceneEntrance>
  <CutsceneEntranceNum>0</CutsceneEntranceNum>
  <CutsceneFlag>0</CutsceneFlag>
  <CutsceneTableRow>-1</CutsceneTableRow>
  <version>4864</version>
  <SegmentFunctions>
    <Capacity>8</Capacity>
    <ZSegmentFunction>
      <Functions>
        <Capacity>0</Capacity>
      </Functions>
    </ZSegmentFunction>
    <ZSegmentFunction>
      <Functions>
        <Capacity>0</Capacity>
      </Functions>
    </ZSegmentFunction>
    <ZSegmentFunction>
      <Functions>
        <Capacity>0</Capacity>
      </Functions>
    </ZSegmentFunction>
    <ZSegmentFunction>
      <Functions>
        <Capacity>0</Capacity>
      </Functions>
    </ZSegmentFunction>
    <ZSegmentFunction>
      <Functions>
        <Capacity>0</Capacity>
      </Functions>
    </ZSegmentFunction>
    <ZSegmentFunction>
      <Functions>
        <Capacity>0</Capacity>
      </Functions>
    </ZSegmentFunction>
    <ZSegmentFunction>
      <Functions>
        <Capacity>0</Capacity>
      </Functions>
    </ZSegmentFunction>
    <ZSegmentFunction>
      <Functions>
        <Capacity>0</Capacity>
      </Functions>
    </ZSegmentFunction>
  </SegmentFunctions>
  <prerenderimages>
    <Capacity>0</Capacity>
  </prerenderimages>
  <CollisionFilename></CollisionFilename>
  <Transitions>
    <Capacity>0</Capacity>
  </Transitions>
  <SpawnPoints>
    <Capacity>4</Capacity>
    <ZActor>
      <Number>0</Number>
      <XPos>0</XPos>
      <YPos>0</YPos>
      <ZPos>0</ZPos>
      <XRot>0</XRot>
      <YRot>0</YRot>
      <ZRot>0</ZRot>
      <Variable>4095</Variable>
      <FrontSwitchTo>0</FrontSwitchTo>
      <FrontCamera>255</FrontCamera>
      <BackSwitchTo>1</BackSwitchTo>
      <BackCamera>255</BackCamera>
      <SpawnRoom>255</SpawnRoom>
    </ZActor>
  </SpawnPoints>
  <Environments>
    <Capacity>8</Capacity>
    <ZEnvironment>
      <C1>-12178119</C1>
      <C2>4802889</C2>
      <C3>-4941174</C3>
      <C4>12040119</C4>
      <C5>-15461316</C5>
      <FogColor>-7571346</FogColor>
      <FogDistance>993</FogDistance>
      <DrawDistance>12800</DrawDistance>
      <FogUnknown>1</FogUnknown>
    </ZEnvironment>
    <ZEnvironment>
      <C1>-9872806</C1>
      <C2>4802889</C2>
      <C3>-16</C3>
      <C4>12040119</C4>
      <C5>-13487526</C5>
      <FogColor>-10197896</FogColor>
      <FogDistance>996</FogDistance>
      <DrawDistance>12800</DrawDistance>
      <FogUnknown>1</FogUnknown>
    </ZEnvironment>
    <ZEnvironment>
      <C1>-8889856</C1>
      <C2>4802889</C2>
      <C3>-358606</C3>
      <C4>12040119</C4>
      <C5>-14803396</C5>
      <FogColor>-8894926</FogColor>
      <FogDistance>995</FogDistance>
      <DrawDistance>12800</DrawDistance>
      <FogUnknown>1</FogUnknown>
    </ZEnvironment>
    <ZEnvironment>
      <C1>-14137756</C1>
      <C2>4802889</C2>
      <C3>-15461341</C3>
      <C4>12040119</C4>
      <C5>-13487516</C5>
      <FogColor>-16777186</FogColor>
      <FogDistance>992</FogDistance>
      <DrawDistance>12800</DrawDistance>
      <FogUnknown>1</FogUnknown>
    </ZEnvironment>
    <ZEnvironment>
      <C1>-12834746</C1>
      <C2>4802889</C2>
      <C3>-11526596</C3>
      <C4>12040119</C4>
      <C5>-11521386</C5>
      <FogColor>-12178643</FogColor>
      <FogDistance>978</FogDistance>
      <DrawDistance>12800</DrawDistance>
      <FogUnknown>63</FogUnknown>
    </ZEnvironment>
    <ZEnvironment>
      <C1>-11838876</C1>
      <C2>4802889</C2>
      <C3>-13107216</C3>
      <C4>12040119</C4>
      <C5>-16083266</C5>
      <FogColor>-15443346</FogColor>
      <FogDistance>978</FogDistance>
      <DrawDistance>12800</DrawDistance>
      <FogUnknown>63</FogUnknown>
    </ZEnvironment>
    <ZEnvironment>
      <C1>-12834736</C1>
      <C2>4802889</C2>
      <C3>-12825706</C3>
      <C4>12040119</C4>
      <C5>-12830826</C5>
      <FogColor>-13492706</FogColor>
      <FogDistance>978</FogDistance>
      <DrawDistance>12800</DrawDistance>
      <FogUnknown>63</FogUnknown>
    </ZEnvironment>
    <ZEnvironment>
      <C1>-16766896</C1>
      <C2>4802889</C2>
      <C3>-15453621</C3>
      <C4>12040119</C4>
      <C5>-13474666</C5>
      <FogColor>-16774636</FogColor>
      <FogDistance>978</FogDistance>
      <DrawDistance>12800</DrawDistance>
      <FogUnknown>63</FogUnknown>
    </ZEnvironment>
  </Environments>
  <Waterboxes>
    <Capacity>0</Capacity>
  </Waterboxes>
  <PolyTypes>
    <Capacity>4</Capacity>
    <ZColPolyType>
      <Raw>0</Raw>
      <PolyFlagA>0</PolyFlagA>
      <PolyFlagB>0</PolyFlagB>
    </ZColPolyType>
  </PolyTypes>
  <ExitList>
    <Capacity>0</Capacity>
  </ExitList>
  <Pathways>
    <Capacity>0</Capacity>
  </Pathways>
  <Cutscene>
    <Capacity>0</Capacity>
  </Cutscene>
  <Cameras>
    <Capacity>0</Capacity>
  </Cameras>
  <SceneHeaders>
    <Capacity>0</Capacity>
  </SceneHeaders>
  <AdditionalTextures>
    <Capacity>0</Capacity>
  </AdditionalTextures>
  <TextureAnims>
    <Capacity>0</Capacity>
  </TextureAnims>
  <Rooms>
    <Capacity>0</Capacity>
  </Rooms>
</ZScene>